athena_vector_cli/__init__.py
athena_vector_cli/cli.py
athena_vector_cli/cli_old.py
athena_vector_cli/config.py
athena_vector_cli/core_integration.py
athena_vector_cli/executor.py
athena_vector_cli/gateway_integration.py
athena_vector_cli/pipeline.py
athena_vector_cli/safety_scorer.py
athena_vector_cli/server.py
athena_vector_cli-0.1.5.dist-info/licenses/LICENSE
athena_vector_cli-0.1.5.dist-info/METADATA
athena_vector_cli-0.1.5.dist-info/WHEEL
athena_vector_cli-0.1.5.dist-info/entry_points.txt
athena_vector_cli-0.1.5.dist-info/top_level.txt
athena_vector_cli-0.1.5.dist-info/RECORD
