Metadata-Version: 2.4
Name: athena-vector-cli
Version: 0.1.5
Summary: Athena Vector Command CLI - 자연어 명령어를 벡터 시스템으로 실행
Home-page: https://github.com/mkmlab-hq/athena-vector-cli
Author: MKM Lab
Author-email: MKM Lab <contact@mkmlab.com>
License-Expression: MIT
Keywords: vector,cli,command,nlp,athena
Classifier: Development Status :: 3 - Alpha
Classifier: Intended Audience :: Developers
Classifier: Programming Language :: Python :: 3
Classifier: Programming Language :: Python :: 3.8
Classifier: Programming Language :: Python :: 3.9
Classifier: Programming Language :: Python :: 3.10
Classifier: Programming Language :: Python :: 3.11
Requires-Python: >=3.8
License-File: LICENSE
Requires-Dist: athena-brain-core>=0.1.0
Requires-Dist: qdrant-client>=1.15.1
Requires-Dist: sentence-transformers>=5.1.2
Requires-Dist: numpy>=1.24.3
Requires-Dist: python-dotenv>=1.0.0
Requires-Dist: pyyaml>=6.0
Provides-Extra: dev
Requires-Dist: pytest>=7.4.0; extra == "dev"
Requires-Dist: black>=23.0.0; extra == "dev"
Requires-Dist: flake8>=6.0.0; extra == "dev"
Dynamic: author
Dynamic: home-page
Dynamic: license-file
Dynamic: requires-python
